Metadata-Version: 2.1
Name: Django-Forwarded
Version: 0.0.1
Summary: Support HTTP "Forwarded" header in your Django applications
Home-page: https://gitlab.cern.ch/skhajanc/django-forwarded
Author: Shreyansh Khajanchi
Author-email: shreyansh.khajanchi@cern.ch
License: Apache License 2.0
Platform: UNKNOWN
Classifier: Programming Language :: Python :: 3
Classifier: License :: OSI Approved :: Apache Software License
Classifier: Operating System :: OS Independent
Classifier: Environment :: Web Environment
Classifier: Intended Audience :: Developers
Classifier: Topic :: Internet :: WWW/HTTP :: Dynamic Content
Classifier: Topic :: Software Development :: Libraries :: Python Modules
Requires-Python: >=3.6
